ioccheck/__init__.py
ioccheck/__main__.py
ioccheck/cli/__init__.py
ioccheck/cli/formatters/__init__.py
ioccheck/cli/formatters/formatter.py
ioccheck/cli/formatters/malwarebazaar.py
ioccheck/cli/formatters/shodan.py
ioccheck/cli/formatters/virustotal.py
ioccheck/exceptions.py
ioccheck/ioc_types.py
ioccheck/iocs/__init__.py
ioccheck/iocs/hash.py
ioccheck/iocs/ioc.py
ioccheck/iocs/ip.py
ioccheck/services/__init__.py
ioccheck/services/malwarebazaar.py
ioccheck/services/service.py
ioccheck/services/shodan.py
ioccheck/services/virustotal.py
ioccheck-0.3.1.dist-info/entry_points.txt
ioccheck-0.3.1.dist-info/LICENSE
ioccheck-0.3.1.dist-info/WHEEL
ioccheck-0.3.1.dist-info/METADATA
ioccheck-0.3.1.dist-info/RECORD
