Metadata-Version: 2.1
Name: ioccheck
Version: 0.3.1
Summary: A tool for simplifying the process of researching IOCs.
Author: ranguli
Author-email: hello@joshmurphy.ca
Requires-Python: >=3.7.3,<4.0.0
Classifier: Programming Language :: Python :: 3
Classifier: Programming Language :: Python :: 3.8
Classifier: Programming Language :: Python :: 3.9
Requires-Dist: backoff (>=1.10.0,<2.0.0)
Requires-Dist: click (>=7.1.2,<8.0.0)
Requires-Dist: hurry.filesize (>=0.9,<0.10)
Requires-Dist: pyfiglet (>=0.8.post1,<0.9)
Requires-Dist: ratelimit (>=2.2.1,<3.0.0)
Requires-Dist: requests (>=2.25.1,<3.0.0)
Requires-Dist: shodan (>=1.25.0,<2.0.0)
Requires-Dist: tabulate (>=0.8.9,<0.9.0)
Requires-Dist: termcolor (>=1.1.0,<2.0.0)
Requires-Dist: vt-py (>=0.6.1,<0.7.0)
